{
  "url": "https://techcrunch.com/2025/06/23/leak-reveals-grok-might-soon-edit-your-spreadsheets/?utm_source=tldrai",
  "title": "Grok Leak Hints at Spreadsheet Editing",
  "content": "[CONTENT EXTRACTION FAILED] Unable to extract content from: https://techcrunch.com/2025/06/23/leak-reveals-grok-might-soon-edit-your-spreadsheets/?utm_source=tldrai",
  "published_date": "2025-06-24 00:00:00",
  "category": "ai",
  "word_count": 0,
  "content_extraction_status": "failed",
  "failure_reason": "Content validation failed - content too short, paywall detected, or formatting issues",
  "feed_name": "TLDR AI",
  "scraped_at": "2025-06-28T00:42:10.623117"
}